{
    "swagger": "2.0",
    "info": {
        "description": "REST API for LDAP user and group management.",
        "title": "ldap-admin-tool API",
        "contact": {},
        "version": "1.0"
    },
    "host": "localhost:8080",
    "basePath": "/api/v1",
    "paths": {
        "/groups": {
            "get": {
                "security": [
                    {
                        "ApiKeyAuth": []
                    }
                ],
                "produces": [
                    "application/json"
                ],
                "tags": [
                    "groups"
                ],
                "summary": "List all groups",
                "responses": {
                    "200": {
                        "description": "OK",
                        "schema": {
                            "type": "array",
                            "items": {
                                "$ref": "#/definitions/types.GroupDetails"
                            }
                        }
                    },
                    "500": {
                        "description": "Internal Server Error",
                        "schema": {
                            "$ref": "#/definitions/api.ErrorResponse"
                        }
                    }
                }
            },
            "post": {
                "security": [
                    {
                        "ApiKeyAuth": []
                    }
                ],
                "consumes": [
                    "application/json"
                ],
                "produces": [
                    "application/json"
                ],
                "tags": [
                    "groups"
                ],
                "summary": "Create a new group",
                "parameters": [
                    {
                        "description": "Group creation request",
                        "name": "body",
                        "in": "body",
                        "required": true,
                        "schema": {
                            "$ref": "#/definitions/api.CreateGroupRequest"
                        }
                    }
                ],
                "responses": {
                    "201": {
                        "description": "Created",
                        "schema": {
                            "$ref": "#/definitions/types.GroupDetails"
                        }
                    },
                    "400": {
                        "description": "Bad Request",
                        "schema": {
                            "$ref": "#/definitions/api.ErrorResponse"
                        }
                    },
                    "500": {
                        "description": "Internal Server Error",
                        "schema": {
                            "$ref": "#/definitions/api.ErrorResponse"
                        }
                    }
                }
            }
        },
        "/groups/{name}": {
            "get": {
                "security": [
                    {
                        "ApiKeyAuth": []
                    }
                ],
                "produces": [
                    "application/json"
                ],
                "tags": [
                    "groups"
                ],
                "summary": "Get a group by name",
                "parameters": [
                    {
                        "type": "string",
                        "description": "Group name",
                        "name": "name",
                        "in": "path",
                        "required": true
                    }
                ],
                "responses": {
                    "200": {
                        "description": "OK",
                        "schema": {
                            "$ref": "#/definitions/types.GroupDetails"
                        }
                    },
                    "404": {
                        "description": "Not Found",
                        "schema": {
                            "$ref": "#/definitions/api.ErrorResponse"
                        }
                    },
                    "500": {
                        "description": "Internal Server Error",
                        "schema": {
                            "$ref": "#/definitions/api.ErrorResponse"
                        }
                    }
                }
            },
            "delete": {
                "security": [
                    {
                        "ApiKeyAuth": []
                    }
                ],
                "produces": [
                    "application/json"
                ],
                "tags": [
                    "groups"
                ],
                "summary": "Delete a group",
                "parameters": [
                    {
                        "type": "string",
                        "description": "Group name",
                        "name": "name",
                        "in": "path",
                        "required": true
                    }
                ],
                "responses": {
                    "204": {
                        "description": "No Content"
                    },
                    "404": {
                        "description": "Not Found",
                        "schema": {
                            "$ref": "#/definitions/api.ErrorResponse"
                        }
                    },
                    "500": {
                        "description": "Internal Server Error",
                        "schema": {
                            "$ref": "#/definitions/api.ErrorResponse"
                        }
                    }
                }
            }
        },
        "/groups/{name}/members": {
            "post": {
                "security": [
                    {
                        "ApiKeyAuth": []
                    }
                ],
                "consumes": [
                    "application/json"
                ],
                "produces": [
                    "application/json"
                ],
                "tags": [
                    "groups"
                ],
                "summary": "Add members to a group",
                "parameters": [
                    {
                        "type": "string",
                        "description": "Group name",
                        "name": "name",
                        "in": "path",
                        "required": true
                    },
                    {
                        "description": "UIDs to add",
                        "name": "body",
                        "in": "body",
                        "required": true,
                        "schema": {
                            "$ref": "#/definitions/api.GroupMembersRequest"
                        }
                    }
                ],
                "responses": {
                    "204": {
                        "description": "No Content"
                    },
                    "400": {
                        "description": "Bad Request",
                        "schema": {
                            "$ref": "#/definitions/api.ErrorResponse"
                        }
                    },
                    "500": {
                        "description": "Internal Server Error",
                        "schema": {
                            "$ref": "#/definitions/api.ErrorResponse"
                        }
                    }
                }
            },
            "delete": {
                "security": [
                    {
                        "ApiKeyAuth": []
                    }
                ],
                "consumes": [
                    "application/json"
                ],
                "produces": [
                    "application/json"
                ],
                "tags": [
                    "groups"
                ],
                "summary": "Remove members from a group",
                "parameters": [
                    {
                        "type": "string",
                        "description": "Group name",
                        "name": "name",
                        "in": "path",
                        "required": true
                    },
                    {
                        "description": "UIDs to remove",
                        "name": "body",
                        "in": "body",
                        "required": true,
                        "schema": {
                            "$ref": "#/definitions/api.GroupMembersRequest"
                        }
                    }
                ],
                "responses": {
                    "204": {
                        "description": "No Content"
                    },
                    "400": {
                        "description": "Bad Request",
                        "schema": {
                            "$ref": "#/definitions/api.ErrorResponse"
                        }
                    },
                    "500": {
                        "description": "Internal Server Error",
                        "schema": {
                            "$ref": "#/definitions/api.ErrorResponse"
                        }
                    }
                }
            }
        },
        "/users": {
            "get": {
                "security": [
                    {
                        "ApiKeyAuth": []
                    }
                ],
                "produces": [
                    "application/json"
                ],
                "tags": [
                    "users"
                ],
                "summary": "List all users",
                "responses": {
                    "200": {
                        "description": "OK",
                        "schema": {
                            "type": "array",
                            "items": {
                                "$ref": "#/definitions/types.UserDetails"
                            }
                        }
                    },
                    "500": {
                        "description": "Internal Server Error",
                        "schema": {
                            "$ref": "#/definitions/api.ErrorResponse"
                        }
                    }
                }
            },
            "post": {
                "security": [
                    {
                        "ApiKeyAuth": []
                    }
                ],
                "consumes": [
                    "application/json"
                ],
                "produces": [
                    "application/json"
                ],
                "tags": [
                    "users"
                ],
                "summary": "Create a new user",
                "parameters": [
                    {
                        "description": "User creation request",
                        "name": "body",
                        "in": "body",
                        "required": true,
                        "schema": {
                            "$ref": "#/definitions/api.CreateUserRequest"
                        }
                    }
                ],
                "responses": {
                    "201": {
                        "description": "Created",
                        "schema": {
                            "$ref": "#/definitions/api.CreateUserResponse"
                        }
                    },
                    "400": {
                        "description": "Bad Request",
                        "schema": {
                            "$ref": "#/definitions/api.ErrorResponse"
                        }
                    },
                    "500": {
                        "description": "Internal Server Error",
                        "schema": {
                            "$ref": "#/definitions/api.ErrorResponse"
                        }
                    }
                }
            }
        },
        "/users/{uid}": {
            "get": {
                "security": [
                    {
                        "ApiKeyAuth": []
                    }
                ],
                "produces": [
                    "application/json"
                ],
                "tags": [
                    "users"
                ],
                "summary": "Get a user by UID",
                "parameters": [
                    {
                        "type": "string",
                        "description": "Username",
                        "name": "uid",
                        "in": "path",
                        "required": true
                    }
                ],
                "responses": {
                    "200": {
                        "description": "OK",
                        "schema": {
                            "$ref": "#/definitions/types.UserDetails"
                        }
                    },
                    "404": {
                        "description": "Not Found",
                        "schema": {
                            "$ref": "#/definitions/api.ErrorResponse"
                        }
                    },
                    "500": {
                        "description": "Internal Server Error",
                        "schema": {
                            "$ref": "#/definitions/api.ErrorResponse"
                        }
                    }
                }
            },
            "delete": {
                "security": [
                    {
                        "ApiKeyAuth": []
                    }
                ],
                "produces": [
                    "application/json"
                ],
                "tags": [
                    "users"
                ],
                "summary": "Delete a user",
                "parameters": [
                    {
                        "type": "string",
                        "description": "Username",
                        "name": "uid",
                        "in": "path",
                        "required": true
                    }
                ],
                "responses": {
                    "204": {
                        "description": "No Content"
                    },
                    "404": {
                        "description": "Not Found",
                        "schema": {
                            "$ref": "#/definitions/api.ErrorResponse"
                        }
                    },
                    "500": {
                        "description": "Internal Server Error",
                        "schema": {
                            "$ref": "#/definitions/api.ErrorResponse"
                        }
                    }
                }
            }
        },
        "/users/{uid}/email": {
            "put": {
                "security": [
                    {
                        "ApiKeyAuth": []
                    }
                ],
                "consumes": [
                    "application/json"
                ],
                "produces": [
                    "application/json"
                ],
                "tags": [
                    "users"
                ],
                "summary": "Change a user's email",
                "parameters": [
                    {
                        "type": "string",
                        "description": "Username",
                        "name": "uid",
                        "in": "path",
                        "required": true
                    },
                    {
                        "description": "New email address",
                        "name": "body",
                        "in": "body",
                        "required": true,
                        "schema": {
                            "$ref": "#/definitions/api.ChangeEmailRequest"
                        }
                    }
                ],
                "responses": {
                    "204": {
                        "description": "No Content"
                    },
                    "400": {
                        "description": "Bad Request",
                        "schema": {
                            "$ref": "#/definitions/api.ErrorResponse"
                        }
                    },
                    "500": {
                        "description": "Internal Server Error",
                        "schema": {
                            "$ref": "#/definitions/api.ErrorResponse"
                        }
                    }
                }
            }
        },
        "/users/{uid}/groups": {
            "post": {
                "security": [
                    {
                        "ApiKeyAuth": []
                    }
                ],
                "consumes": [
                    "application/json"
                ],
                "produces": [
                    "application/json"
                ],
                "tags": [
                    "users"
                ],
                "summary": "Add a user to groups",
                "parameters": [
                    {
                        "type": "string",
                        "description": "Username",
                        "name": "uid",
                        "in": "path",
                        "required": true
                    },
                    {
                        "description": "Groups to add",
                        "name": "body",
                        "in": "body",
                        "required": true,
                        "schema": {
                            "$ref": "#/definitions/api.UserGroupsRequest"
                        }
                    }
                ],
                "responses": {
                    "204": {
                        "description": "No Content"
                    },
                    "400": {
                        "description": "Bad Request",
                        "schema": {
                            "$ref": "#/definitions/api.ErrorResponse"
                        }
                    },
                    "500": {
                        "description": "Internal Server Error",
                        "schema": {
                            "$ref": "#/definitions/api.ErrorResponse"
                        }
                    }
                }
            },
            "delete": {
                "security": [
                    {
                        "ApiKeyAuth": []
                    }
                ],
                "consumes": [
                    "application/json"
                ],
                "produces": [
                    "application/json"
                ],
                "tags": [
                    "users"
                ],
                "summary": "Remove a user from groups",
                "parameters": [
                    {
                        "type": "string",
                        "description": "Username",
                        "name": "uid",
                        "in": "path",
                        "required": true
                    },
                    {
                        "description": "Groups to remove from",
                        "name": "body",
                        "in": "body",
                        "required": true,
                        "schema": {
                            "$ref": "#/definitions/api.UserGroupsRequest"
                        }
                    }
                ],
                "responses": {
                    "204": {
                        "description": "No Content"
                    },
                    "400": {
                        "description": "Bad Request",
                        "schema": {
                            "$ref": "#/definitions/api.ErrorResponse"
                        }
                    },
                    "500": {
                        "description": "Internal Server Error",
                        "schema": {
                            "$ref": "#/definitions/api.ErrorResponse"
                        }
                    }
                }
            }
        },
        "/users/{uid}/password": {
            "put": {
                "security": [
                    {
                        "ApiKeyAuth": []
                    }
                ],
                "consumes": [
                    "application/json"
                ],
                "produces": [
                    "application/json"
                ],
                "tags": [
                    "users"
                ],
                "summary": "Change a user's password",
                "parameters": [
                    {
                        "type": "string",
                        "description": "Username",
                        "name": "uid",
                        "in": "path",
                        "required": true
                    },
                    {
                        "description": "Leave password empty to auto-generate",
                        "name": "body",
                        "in": "body",
                        "schema": {
                            "$ref": "#/definitions/api.ChangePasswordRequest"
                        }
                    }
                ],
                "responses": {
                    "200": {
                        "description": "OK",
                        "schema": {
                            "$ref": "#/definitions/api.ChangePasswordResponse"
                        }
                    },
                    "400": {
                        "description": "Bad Request",
                        "schema": {
                            "$ref": "#/definitions/api.ErrorResponse"
                        }
                    },
                    "500": {
                        "description": "Internal Server Error",
                        "schema": {
                            "$ref": "#/definitions/api.ErrorResponse"
                        }
                    }
                }
            }
        }
    },
    "definitions": {
        "api.ChangeEmailRequest": {
            "type": "object",
            "required": [
                "email"
            ],
            "properties": {
                "email": {
                    "type": "string",
                    "example": "newemail@example.com"
                }
            }
        },
        "api.ChangePasswordRequest": {
            "type": "object",
            "properties": {
                "password": {
                    "type": "string",
                    "example": "NewP@ss123!"
                }
            }
        },
        "api.ChangePasswordResponse": {
            "type": "object",
            "properties": {
                "password": {
                    "type": "string"
                }
            }
        },
        "api.CreateGroupRequest": {
            "type": "object",
            "required": [
                "name"
            ],
            "properties": {
                "gid": {
                    "type": "integer",
                    "example": 10050
                },
                "name": {
                    "type": "string",
                    "example": "printing-c"
                }
            }
        },
        "api.CreateUserRequest": {
            "type": "object",
            "required": [
                "email",
                "first_name",
                "last_name"
            ],
            "properties": {
                "email": {
                    "type": "string",
                    "example": "jdoe@example.com"
                },
                "first_name": {
                    "type": "string",
                    "example": "John"
                },
                "gid": {
                    "type": "integer",
                    "example": 10008
                },
                "groups": {
                    "type": "array",
                    "items": {
                        "type": "string"
                    }
                },
                "last_name": {
                    "type": "string",
                    "example": "Doe"
                },
                "password": {
                    "type": "string",
                    "example": "MyP@ss123!"
                },
                "send_email": {
                    "type": "boolean",
                    "example": true
                },
                "send_pdf": {
                    "type": "boolean",
                    "example": true
                },
                "uid": {
                    "type": "string",
                    "example": "jdoe"
                }
            }
        },
        "api.CreateUserResponse": {
            "type": "object",
            "properties": {
                "email_sent": {
                    "type": "boolean"
                },
                "groups": {
                    "type": "array",
                    "items": {
                        "type": "string"
                    }
                },
                "uid": {
                    "type": "string"
                },
                "uid_number": {
                    "type": "integer"
                }
            }
        },
        "api.ErrorResponse": {
            "type": "object",
            "properties": {
                "error": {
                    "type": "string",
                    "example": "user 'jdoe' not found"
                }
            }
        },
        "api.GroupMembersRequest": {
            "type": "object",
            "required": [
                "uids"
            ],
            "properties": {
                "uids": {
                    "type": "array",
                    "items": {
                        "type": "string"
                    }
                }
            }
        },
        "api.UserGroupsRequest": {
            "type": "object",
            "required": [
                "groups"
            ],
            "properties": {
                "groups": {
                    "type": "array",
                    "items": {
                        "type": "string"
                    }
                }
            }
        },
        "types.GroupDetails": {
            "type": "object",
            "properties": {
                "dn": {
                    "type": "string"
                },
                "gid": {
                    "type": "integer"
                },
                "members": {
                    "type": "array",
                    "items": {
                        "type": "string"
                    }
                },
                "name": {
                    "type": "string"
                }
            }
        },
        "types.UserDetails": {
            "type": "object",
            "properties": {
                "dn": {
                    "type": "string"
                },
                "email": {
                    "type": "string"
                },
                "first_name": {
                    "type": "string"
                },
                "gid_number": {
                    "type": "integer"
                },
                "groups": {
                    "type": "array",
                    "items": {
                        "type": "string"
                    }
                },
                "home_dir": {
                    "type": "string"
                },
                "last_name": {
                    "type": "string"
                },
                "shell": {
                    "type": "string"
                },
                "uid": {
                    "type": "string"
                },
                "uid_number": {
                    "type": "integer"
                }
            }
        }
    },
    "securityDefinitions": {
        "ApiKeyAuth": {
            "type": "apiKey",
            "name": "X-Api-Key",
            "in": "header"
        }
    }
}